LICENSE.txt
MANIFEST.in
README.txt
setup.py
pcart_plugins/__init__.py
pcart_plugins/cms_plugins.py
pcart_plugins/forms.py
pcart_plugins/models.py
pcart_plugins/settings.py
pcart_plugins.egg-info/PKG-INFO
pcart_plugins.egg-info/SOURCES.txt
pcart_plugins.egg-info/dependency_links.txt
pcart_plugins.egg-info/not-zip-safe
pcart_plugins.egg-info/requires.txt
pcart_plugins.egg-info/top_level.txt
pcart_plugins/locale/ru/LC_MESSAGES/django.mo
pcart_plugins/locale/ru/LC_MESSAGES/django.po
pcart_plugins/locale/uk/LC_MESSAGES/django.mo
pcart_plugins/locale/uk/LC_MESSAGES/django.po
pcart_plugins/migrations/0001_initial.py
pcart_plugins/migrations/0002_auto_20171002_1521.py
pcart_plugins/migrations/0003_auto_20171002_1526.py
pcart_plugins/migrations/0004_auto_20171002_1534.py
pcart_plugins/migrations/__init__.py